BroAnalytics/__init__.py
BroAnalytics-0.1.0.dist-info/METADATA
BroAnalytics-0.1.0.dist-info/WHEEL
BroAnalytics-0.1.0.dist-info/top_level.txt
BroAnalytics-0.1.0.dist-info/RECORD
